{
  "exportDate": "2025-08-28 03:21:23",
  "account": "ZI*******64",
  "date": "2025-08-26",
  "trades": [
    {
      "date": "2025-08-26",
      "opened": "08/26/25 07:37:36",
      "closed": "07:44:59",
      "held": "00:07:23",
      "symbol": "VRAX",
      "type": "Short",
      "entry": 1.11,
      "exit": 0.9984,
      "size": 16.0,
      "pnl": 1.79,
      "commission": 0.05,
      "net": 1.74,
      "account": "ZIMDASE9C64",
      "side": "SELL",
      "quantity": 16.0,
      "price": 1.11
    },
    {
      "date": "2025-08-26",
      "opened": "08/26/25 07:38:26",
      "closed": "07:58:47",
      "held": "00:20:21",
      "symbol": "IVVD",
      "type": "Long",
      "entry": 1.3233,
      "exit": 1.2742,
      "size": 48.0,
      "pnl": -2.36,
      "commission": 0.14,
      "net": -2.55,
      "account": "ZIMDASE9C64",
      "side": "BUY",
      "quantity": 48.0,
      "price": 1.3233
    },
    {
      "date": "2025-08-26",
      "opened": "08/26/25 07:52:10",
      "closed": "08:12:38",
      "held": "00:20:28",
      "symbol": "AIFF",
      "type": "Short",
      "entry": 3.5067,
      "exit": 3.3443,
      "size": 60.0,
      "pnl": 9.74,
      "commission": 0.18,
      "net": 9.54,
      "account": "ZIMDASE9C64",
      "side": "SELL",
      "quantity": 60.0,
      "price": 3.5067
    },
    {
      "date": "2025-08-26",
      "opened": "08/26/25 09:03:17",
      "closed": "11:44:48",
      "held": "02:41:31",
      "symbol": "INHD",
      "type": "Short",
      "entry": 3.619,
      "exit": 3.4435,
      "size": 204.0,
      "pnl": 35.81,
      "commission": 0.61,
      "net": 34.46,
      "account": "ZIMDASE9C64",
      "side": "SELL",
      "quantity": 204.0,
      "price": 3.619
    },
    {
      "date": "2025-08-26",
      "opened": "08/26/25 10:01:45",
      "closed": "10:18:40",
      "held": "00:16:55",
      "symbol": "ALLR",
      "type": "Short",
      "entry": 1.8691,
      "exit": 2.023,
      "size": 88.0,
      "pnl": -13.54,
      "commission": 0.26,
      "net": -14.0,
      "account": "ZIMDASE9C64",
      "side": "SELL",
      "quantity": 88.0,
      "price": 1.8691
    },
    {
      "date": "2025-08-26",
      "opened": "08/26/25 10:19:27",
      "closed": "10:31:25",
      "held": "00:11:58",
      "symbol": "ALLR",
      "type": "Long",
      "entry": 2.1139,
      "exit": 2.1299,
      "size": 324.0,
      "pnl": 5.19,
      "commission": 0.97,
      "net": 3.91,
      "account": "ZIMDASE9C64",
      "side": "BUY",
      "quantity": 324.0,
      "price": 2.1139
    },
    {
      "date": "2025-08-26",
      "opened": "08/26/25 10:31:58",
      "closed": "11:10:41",
      "held": "00:38:43",
      "symbol": "ALLR",
      "type": "Long",
      "entry": 2.0357,
      "exit": 2.0709,
      "size": 768.0,
      "pnl": 26.99,
      "commission": 2.3,
      "net": 24.01,
      "account": "ZIMDASE9C64",
      "side": "BUY",
      "quantity": 768.0,
      "price": 2.0357
    },
    {
      "date": "2025-08-26",
      "opened": "08/26/25 11:00:12",
      "closed": "11:27:04",
      "held": "00:26:52",
      "symbol": "HKPD",
      "type": "Short",
      "entry": 1.9501,
      "exit": 1.7392,
      "size": 12.0,
      "pnl": 2.53,
      "commission": 0.04,
      "net": 2.45,
      "account": "ZIMDASE9C64",
      "side": "SELL",
      "quantity": 12.0,
      "price": 1.9501
    }
  ],
  "summary": {
    "totalTrades": 8,
    "totalPnL": 66.15,
    "totalCommissions": 4.55,
    "netPnL": 59.56,
    "winningTrades": 6,
    "losingTrades": 2,
    "symbols": [
      "VRAX",
      "INHD",
      "ALLR",
      "AIFF",
      "HKPD",
      "IVVD"
    ]
  },
  "metadata": {
    "reprocessed": true,
    "processedAt": "2025-08-28 03:21:23"
  }
}