{
  "exportDate": "2025-07-27 05:29:52",
  "account": "ZI*******64",
  "date": "2025-06-13",
  "trades": [
    {
      "date": "2025-06-13",
      "opened": "06/13/25 05:53:04",
      "closed": "05:59:45",
      "held": "00:06:41",
      "symbol": "INDO",
      "type": "Long",
      "entry": 5.62,
      "exit": 5.4383,
      "size": 6.0,
      "pnl": -1.09,
      "commission": 0.02,
      "net": -1.14,
      "account": "ZIMDASE9C64",
      "side": "BUY",
      "quantity": 6.0,
      "price": 5.62
    },
    {
      "date": "2025-06-13",
      "opened": "06/13/25 06:15:20",
      "closed": "08:47:59",
      "held": "02:32:39",
      "symbol": "TPET",
      "type": "Long",
      "entry": 1.585,
      "exit": 1.57,
      "size": 12.0,
      "pnl": -0.18,
      "commission": 0.04,
      "net": -0.26,
      "account": "ZIMDASE9C64",
      "side": "BUY",
      "quantity": 12.0,
      "price": 1.585
    },
    {
      "date": "2025-06-13",
      "opened": "06/13/25 06:21:58",
      "closed": "06:28:17",
      "held": "00:06:19",
      "symbol": "IMPP",
      "type": "Long",
      "entry": 3.92,
      "exit": 3.895,
      "size": 2.0,
      "pnl": -0.05,
      "commission": 0.01,
      "net": -0.07,
      "account": "ZIMDASE9C64",
      "side": "BUY",
      "quantity": 2.0,
      "price": 3.92
    },
    {
      "date": "2025-06-13",
      "opened": "06/13/25 06:49:24",
      "closed": "08:59:24",
      "held": "02:10:00",
      "symbol": "USEG",
      "type": "Long",
      "entry": 2.56,
      "exit": 2.67,
      "size": 4.0,
      "pnl": 0.44,
      "commission": 0.01,
      "net": 0.41,
      "account": "ZIMDASE9C64",
      "side": "BUY",
      "quantity": 4.0,
      "price": 2.56
    },
    {
      "date": "2025-06-13",
      "opened": "06/13/25 06:51:02",
      "closed": "06:54:05",
      "held": "00:03:03",
      "symbol": "TMDE",
      "type": "Long",
      "entry": 1.13,
      "exit": 1.255,
      "size": 2.0,
      "pnl": 0.25,
      "commission": 0.01,
      "net": 0.23,
      "account": "ZIMDASE9C64",
      "side": "BUY",
      "quantity": 2.0,
      "price": 1.13
    },
    {
      "date": "2025-06-13",
      "opened": "06/13/25 07:01:09",
      "closed": "07:57:50",
      "held": "00:56:41",
      "symbol": "INDO",
      "type": "Long",
      "entry": 5.0,
      "exit": 4.79,
      "size": 2.0,
      "pnl": -0.42,
      "commission": 0.01,
      "net": -0.44,
      "account": "ZIMDASE9C64",
      "side": "BUY",
      "quantity": 2.0,
      "price": 5.0
    },
    {
      "date": "2025-06-13",
      "opened": "06/13/25 07:01:26",
      "closed": "07:08:19",
      "held": "00:06:53",
      "symbol": "PRZO",
      "type": "Long",
      "entry": 1.37,
      "exit": 1.39,
      "size": 2.0,
      "pnl": 0.04,
      "commission": 0.01,
      "net": 0.02,
      "account": "ZIMDASE9C64",
      "side": "BUY",
      "quantity": 2.0,
      "price": 1.37
    },
    {
      "date": "2025-06-13",
      "opened": "06/13/25 07:30:25",
      "closed": "07:32:20",
      "held": "00:01:55",
      "symbol": "TORO",
      "type": "Long",
      "entry": 2.37,
      "exit": 2.23,
      "size": 2.0,
      "pnl": -0.28,
      "commission": 0.01,
      "net": -0.3,
      "account": "ZIMDASE9C64",
      "side": "BUY",
      "quantity": 2.0,
      "price": 2.37
    },
    {
      "date": "2025-06-13",
      "opened": "06/13/25 08:29:50",
      "closed": "08:59:31",
      "held": "00:29:41",
      "symbol": "RBNE",
      "type": "Long",
      "entry": 9.73,
      "exit": 10.12,
      "size": 4.0,
      "pnl": 1.56,
      "commission": 0.01,
      "net": 1.53,
      "account": "ZIMDASE9C64",
      "side": "BUY",
      "quantity": 4.0,
      "price": 9.73
    },
    {
      "date": "2025-06-13",
      "opened": "06/13/25 09:15:11",
      "closed": "09:30:04",
      "held": "00:14:53",
      "symbol": "RBNE",
      "type": "Long",
      "entry": 11.7743,
      "exit": 11.7822,
      "size": 14.0,
      "pnl": 0.11,
      "commission": 0.04,
      "net": 0.02,
      "account": "ZIMDASE9C64",
      "side": "BUY",
      "quantity": 14.0,
      "price": 11.7743
    },
    {
      "date": "2025-06-13",
      "opened": "06/13/25 09:32:51",
      "closed": "09:33:25",
      "held": "00:00:34",
      "symbol": "RBNE",
      "type": "Long",
      "entry": 11.38,
      "exit": 12.925,
      "size": 2.0,
      "pnl": 3.09,
      "commission": 0.01,
      "net": 3.08,
      "account": "ZIMDASE9C64",
      "side": "BUY",
      "quantity": 2.0,
      "price": 11.38
    },
    {
      "date": "2025-06-13",
      "opened": "06/13/25 09:39:21",
      "closed": "10:33:24",
      "held": "00:54:03",
      "symbol": "USEG",
      "type": "Long",
      "entry": 2.57,
      "exit": 2.695,
      "size": 2.0,
      "pnl": 0.25,
      "commission": 0.01,
      "net": 0.24,
      "account": "ZIMDASE9C64",
      "side": "BUY",
      "quantity": 2.0,
      "price": 2.57
    },
    {
      "date": "2025-06-13",
      "opened": "06/13/25 09:41:08",
      "closed": "10:04:05",
      "held": "00:22:57",
      "symbol": "RBNE",
      "type": "Long",
      "entry": 11.6333,
      "exit": 12.3467,
      "size": 6.0,
      "pnl": 4.28,
      "commission": 0.02,
      "net": 4.26,
      "account": "ZIMDASE9C64",
      "side": "BUY",
      "quantity": 6.0,
      "price": 11.6333
    },
    {
      "date": "2025-06-13",
      "opened": "06/13/25 10:17:08",
      "closed": "10:27:39",
      "held": "00:10:31",
      "symbol": "RBNE",
      "type": "Long",
      "entry": 15.47,
      "exit": 15.8734,
      "size": 6.0,
      "pnl": 2.42,
      "commission": 0.02,
      "net": 2.39,
      "account": "ZIMDASE9C64",
      "side": "BUY",
      "quantity": 6.0,
      "price": 15.47
    },
    {
      "date": "2025-06-13",
      "opened": "06/13/25 10:35:24",
      "closed": "14:51:40",
      "held": "04:16:16",
      "symbol": "ICON",
      "type": "Short",
      "entry": 2.91,
      "exit": 2.8575,
      "size": 4.0,
      "pnl": 0.21,
      "commission": 0.01,
      "net": 0.19,
      "account": "ZIMDASE9C64",
      "side": "SELL",
      "quantity": 4.0,
      "price": 2.91
    },
    {
      "date": "2025-06-13",
      "opened": "06/13/25 10:39:37",
      "closed": "10:45:50",
      "held": "00:06:13",
      "symbol": "RBNE",
      "type": "Long",
      "entry": 15.6,
      "exit": 16.1675,
      "size": 4.0,
      "pnl": 2.27,
      "commission": 0.01,
      "net": 2.25,
      "account": "ZIMDASE9C64",
      "side": "BUY",
      "quantity": 4.0,
      "price": 15.6
    },
    {
      "date": "2025-06-13",
      "opened": "06/13/25 10:48:54",
      "closed": "10:51:17",
      "held": "00:02:23",
      "symbol": "RBNE",
      "type": "Long",
      "entry": 15.8267,
      "exit": 16.4167,
      "size": 3.0,
      "pnl": 1.77,
      "commission": 0.01,
      "net": 1.75,
      "account": "ZIMDASE9C64",
      "side": "BUY",
      "quantity": 3.0,
      "price": 15.8267
    },
    {
      "date": "2025-06-13",
      "opened": "06/13/25 10:54:38",
      "closed": "11:13:42",
      "held": "00:19:04",
      "symbol": "RBNE",
      "type": "Long",
      "entry": 15.7425,
      "exit": 15.6088,
      "size": 8.0,
      "pnl": -1.07,
      "commission": 0.02,
      "net": -1.11,
      "account": "ZIMDASE9C64",
      "side": "BUY",
      "quantity": 8.0,
      "price": 15.7425
    },
    {
      "date": "2025-06-13",
      "opened": "06/13/25 11:17:12",
      "closed": "11:53:35",
      "held": "00:36:23",
      "symbol": "RBNE",
      "type": "Long",
      "entry": 14.3933,
      "exit": 15.14,
      "size": 3.0,
      "pnl": 2.24,
      "commission": 0.01,
      "net": 2.22,
      "account": "ZIMDASE9C64",
      "side": "BUY",
      "quantity": 3.0,
      "price": 14.3933
    },
    {
      "date": "2025-06-13",
      "opened": "06/13/25 12:29:17",
      "closed": "12:54:10",
      "held": "00:24:53",
      "symbol": "RBNE",
      "type": "Long",
      "entry": 15.15,
      "exit": 15.93,
      "size": 1.0,
      "pnl": 0.78,
      "commission": 0.0,
      "net": 0.77,
      "account": "ZIMDASE9C64",
      "side": "BUY",
      "quantity": 1.0,
      "price": 15.15
    },
    {
      "date": "2025-06-13",
      "opened": "06/13/25 12:44:48",
      "closed": "15:18:58",
      "held": "02:34:10",
      "symbol": "HUSA",
      "type": "Short",
      "entry": 15.8795,
      "exit": 15.6621,
      "size": 19.0,
      "pnl": 4.13,
      "commission": 0.06,
      "net": 4.02,
      "account": "ZIMDASE9C64",
      "side": "SELL",
      "quantity": 19.0,
      "price": 15.8795
    },
    {
      "date": "2025-06-13",
      "opened": "06/13/25 14:51:40",
      "closed": "14:52:58",
      "held": "00:01:18",
      "symbol": "ICON",
      "type": "Long",
      "entry": 2.76,
      "exit": 2.79,
      "size": 1.0,
      "pnl": 0.03,
      "commission": 0.0,
      "net": 0.02,
      "account": "ZIMDASE9C64",
      "side": "BUY",
      "quantity": 1.0,
      "price": 2.76
    },
    {
      "date": "2025-06-13",
      "opened": "06/13/25 14:58:47",
      "closed": "15:17:39",
      "held": "00:18:52",
      "symbol": "RBNE",
      "type": "Long",
      "entry": 13.6585,
      "exit": 12.9833,
      "size": 107.0,
      "pnl": -72.25,
      "commission": 0.32,
      "net": -72.4,
      "account": "ZIMDASE9C64",
      "side": "BUY",
      "quantity": 107.0,
      "price": 13.6585
    },
    {
      "date": "2025-06-13",
      "opened": "06/13/25 15:23:01",
      "closed": "15:37:00",
      "held": "00:13:59",
      "symbol": "RBNE",
      "type": "Short",
      "entry": 13.8575,
      "exit": 15.39,
      "size": 8.0,
      "pnl": -12.26,
      "commission": 0.02,
      "net": -12.28,
      "account": "ZIMDASE9C64",
      "side": "SELL",
      "quantity": 8.0,
      "price": 13.8575
    },
    {
      "date": "2025-06-13",
      "opened": "06/13/25 16:33:14",
      "closed": "16:47:55",
      "held": "00:14:41",
      "symbol": "RBNE",
      "type": "Short",
      "entry": 12.75,
      "exit": 12.55,
      "size": 1.0,
      "pnl": 0.2,
      "commission": 0.0,
      "net": 0.19,
      "account": "ZIMDASE9C64",
      "side": "SELL",
      "quantity": 1.0,
      "price": 12.75
    }
  ],
  "summary": {
    "totalTrades": 25,
    "totalPnL": -63.53,
    "totalCommissions": 0.69,
    "netPnL": -64.41,
    "winningTrades": 17,
    "losingTrades": 8,
    "symbols": [
      "HUSA",
      "IMPP",
      "PRZO",
      "INDO",
      "TMDE",
      "TPET",
      "ICON",
      "USEG",
      "TORO",
      "RBNE"
    ]
  },
  "metadata": {
    "reprocessed": true,
    "processedAt": "2025-07-27 05:29:52"
  }
}