{
  "exportDate": "2025-12-27 03:33:50",
  "account": "ZI*******64",
  "date": "2025-12-24",
  "trades": [
    {
      "date": "2025-12-24",
      "opened": "12/24/25 09:31:33",
      "closed": "09:36:42",
      "held": "00:05:09",
      "symbol": "SOBR",
      "type": "Short",
      "entry": 2.2311,
      "exit": 2.5706,
      "size": 580.0,
      "pnl": -196.92,
      "commission": 1.74,
      "net": -198.43,
      "account": "ZIMDASE9C64",
      "side": "SELL",
      "quantity": 580.0,
      "price": 2.2311
    },
    {
      "date": "2025-12-24",
      "opened": "12/24/25 09:34:39",
      "closed": "09:53:22",
      "held": "00:18:43",
      "symbol": "DRMA",
      "type": "Short",
      "entry": 2.6551,
      "exit": 2.4287,
      "size": 40.0,
      "pnl": 9.05,
      "commission": 0.12,
      "net": 8.95,
      "account": "ZIMDASE9C64",
      "side": "SELL",
      "quantity": 40.0,
      "price": 2.6551
    },
    {
      "date": "2025-12-24",
      "opened": "12/24/25 09:37:01",
      "closed": "10:20:17",
      "held": "00:43:16",
      "symbol": "SOBR",
      "type": "Short",
      "entry": 2.3952,
      "exit": 2.5889,
      "size": 1812.0,
      "pnl": -350.88,
      "commission": 5.44,
      "net": -353.81,
      "account": "ZIMDASE9C64",
      "side": "SELL",
      "quantity": 1812.0,
      "price": 2.3952
    },
    {
      "date": "2025-12-24",
      "opened": "12/24/25 09:39:26",
      "closed": "10:15:04",
      "held": "00:35:38",
      "symbol": "INDP",
      "type": "Short",
      "entry": 3.05,
      "exit": 2.8562,
      "size": 210.0,
      "pnl": 40.7,
      "commission": 0.63,
      "net": 40.4,
      "account": "ZIMDASE9C64",
      "side": "SELL",
      "quantity": 210.0,
      "price": 3.05
    },
    {
      "date": "2025-12-24",
      "opened": "12/24/25 10:23:26",
      "closed": "12:58:58",
      "held": "02:35:32",
      "symbol": "SOBR",
      "type": "Short",
      "entry": 2.5632,
      "exit": 2.3275,
      "size": 1959.0,
      "pnl": 461.69,
      "commission": 5.88,
      "net": 458.68,
      "account": "ZIMDASE9C64",
      "side": "SELL",
      "quantity": 1959.0,
      "price": 2.5632
    },
    {
      "date": "2025-12-24",
      "opened": "12/24/25 11:13:18",
      "closed": "12:56:22",
      "held": "01:43:04",
      "symbol": "INDP",
      "type": "Short",
      "entry": 2.6418,
      "exit": 2.64,
      "size": 110.0,
      "pnl": 0.21,
      "commission": 0.33,
      "net": -0.33,
      "account": "ZIMDASE9C64",
      "side": "SELL",
      "quantity": 110.0,
      "price": 2.6418
    },
    {
      "date": "2025-12-24",
      "opened": "12/24/25 11:31:38",
      "closed": "11:35:39",
      "held": "00:04:01",
      "symbol": "AMCI",
      "type": "Short",
      "entry": 9.7313,
      "exit": 9.3813,
      "size": 80.0,
      "pnl": 28.0,
      "commission": 0.24,
      "net": 27.94,
      "account": "ZIMDASE9C64",
      "side": "SELL",
      "quantity": 80.0,
      "price": 9.7313
    },
    {
      "date": "2025-12-24",
      "opened": "12/24/25 12:38:26",
      "closed": "12:58:40",
      "held": "00:20:14",
      "symbol": "AMCI",
      "type": "Short",
      "entry": 9.8717,
      "exit": 9.5817,
      "size": 60.0,
      "pnl": 17.4,
      "commission": 0.18,
      "net": 17.43,
      "account": "ZIMDASE9C64",
      "side": "SELL",
      "quantity": 60.0,
      "price": 9.8717
    },
    {
      "date": "2025-12-24",
      "opened": "12/24/25 13:00:12",
      "closed": "14:20:24",
      "held": "01:20:12",
      "symbol": "SOBR",
      "type": "Short",
      "entry": 2.3046,
      "exit": 2.3185,
      "size": 130.0,
      "pnl": -1.8,
      "commission": 0.39,
      "net": -2.0,
      "account": "ZIMDASE9C64",
      "side": "SELL",
      "quantity": 130.0,
      "price": 2.3046
    },
    {
      "date": "2025-12-24",
      "opened": "12/24/25 13:35:34",
      "closed": "13:58:17",
      "held": "00:22:43",
      "symbol": "INDP",
      "type": "Short",
      "entry": 2.81,
      "exit": 2.735,
      "size": 20.0,
      "pnl": 1.5,
      "commission": 0.06,
      "net": 1.41,
      "account": "ZIMDASE9C64",
      "side": "SELL",
      "quantity": 20.0,
      "price": 2.81
    }
  ],
  "summary": {
    "totalTrades": 10,
    "totalPnL": 8.95,
    "totalCommissions": 15.01,
    "netPnL": 0.24,
    "winningTrades": 7,
    "losingTrades": 3,
    "symbols": [
      "INDP",
      "SOBR",
      "DRMA",
      "AMCI"
    ]
  },
  "metadata": {
    "reprocessed": true,
    "processedAt": "2025-12-27 03:33:50"
  }
}