{
  "exportDate": "2026-02-15 15:07:44",
  "account": "ZI*******64",
  "date": "2026-02-12",
  "trades": [
    {
      "date": "2026-02-12",
      "opened": "02/12/26 07:01:26",
      "closed": "08:13:19",
      "held": "01:11:53",
      "symbol": "GNLN",
      "type": "Short",
      "entry": 1.27,
      "exit": 1.09,
      "size": 33.0,
      "pnl": 5.94,
      "commission": 0.1,
      "net": 5.63,
      "account": "ZIMDASE9C64",
      "side": "SELL",
      "quantity": 33.0,
      "price": 1.27
    },
    {
      "date": "2026-02-12",
      "opened": "02/12/26 08:00:14",
      "closed": "08:02:06",
      "held": "00:01:52",
      "symbol": "JDZG",
      "type": "Short",
      "entry": 1.56,
      "exit": 1.77,
      "size": 29.0,
      "pnl": -6.09,
      "commission": 0.09,
      "net": -6.22,
      "account": "ZIMDASE9C64",
      "side": "SELL",
      "quantity": 29.0,
      "price": 1.56
    },
    {
      "date": "2026-02-12",
      "opened": "02/12/26 08:09:05",
      "closed": "08:29:46",
      "held": "00:20:41",
      "symbol": "VRME",
      "type": "Short",
      "entry": 1.32,
      "exit": 1.07,
      "size": 35.0,
      "pnl": 8.75,
      "commission": 0.11,
      "net": 8.77,
      "account": "ZIMDASE9C64",
      "side": "SELL",
      "quantity": 35.0,
      "price": 1.32
    },
    {
      "date": "2026-02-12",
      "opened": "02/12/26 08:59:16",
      "closed": "10:09:35",
      "held": "01:10:19",
      "symbol": "SMU",
      "type": "Short",
      "entry": 12.29,
      "exit": 10.57,
      "size": 3.0,
      "pnl": 5.16,
      "commission": 0.01,
      "net": 5.14,
      "account": "ZIMDASE9C64",
      "side": "SELL",
      "quantity": 3.0,
      "price": 12.29
    },
    {
      "date": "2026-02-12",
      "opened": "02/12/26 09:31:05",
      "closed": "10:00:38",
      "held": "00:29:33",
      "symbol": "PMI",
      "type": "Short",
      "entry": 2.2736,
      "exit": 2.085,
      "size": 140.0,
      "pnl": 26.4,
      "commission": 0.42,
      "net": 26.08,
      "account": "ZIMDASE9C64",
      "side": "SELL",
      "quantity": 140.0,
      "price": 2.2736
    },
    {
      "date": "2026-02-12",
      "opened": "02/12/26 09:32:43",
      "closed": "11:23:23",
      "held": "01:50:40",
      "symbol": "QNCX",
      "type": "Short",
      "entry": 0.4088,
      "exit": 0.3243,
      "size": 16.0,
      "pnl": 1.35,
      "commission": 0.05,
      "net": 1.29,
      "account": "ZIMDASE9C64",
      "side": "SELL",
      "quantity": 16.0,
      "price": 0.4088
    },
    {
      "date": "2026-02-12",
      "opened": "02/12/26 10:28:36",
      "closed": "10:51:35",
      "held": "00:22:59",
      "symbol": "JZXN",
      "type": "Short",
      "entry": 2.27,
      "exit": 2.575,
      "size": 20.0,
      "pnl": -6.1,
      "commission": 0.06,
      "net": -6.19,
      "account": "ZIMDASE9C64",
      "side": "SELL",
      "quantity": 20.0,
      "price": 2.27
    },
    {
      "date": "2026-02-12",
      "opened": "02/12/26 12:21:01",
      "closed": "12:22:01",
      "held": "00:01:00",
      "symbol": "TSLA",
      "type": "Long",
      "entry": 418.4699,
      "exit": 418.6,
      "size": 4.0,
      "pnl": 0.52,
      "commission": 0.01,
      "net": 0.5,
      "account": "ZIMDASE9C64",
      "side": "BUY",
      "quantity": 4.0,
      "price": 418.4699
    },
    {
      "date": "2026-02-12",
      "opened": "02/12/26 12:24:05",
      "closed": "12:29:16",
      "held": "00:05:11",
      "symbol": "TSLA",
      "type": "Long",
      "entry": 419.08,
      "exit": 418.8601,
      "size": 4.0,
      "pnl": -0.88,
      "commission": 0.01,
      "net": -0.9,
      "account": "ZIMDASE9C64",
      "side": "BUY",
      "quantity": 4.0,
      "price": 419.08
    },
    {
      "date": "2026-02-12",
      "opened": "02/12/26 12:38:16",
      "closed": "12:38:49",
      "held": "00:00:33",
      "symbol": "TSLA",
      "type": "Long",
      "entry": 419.9399,
      "exit": 419.2601,
      "size": 4.0,
      "pnl": -2.72,
      "commission": 0.01,
      "net": -2.77,
      "account": "ZIMDASE9C64",
      "side": "BUY",
      "quantity": 4.0,
      "price": 419.9399
    },
    {
      "date": "2026-02-12",
      "opened": "02/12/26 15:27:08",
      "closed": "16:51:11",
      "held": "01:24:03",
      "symbol": "FSLY",
      "type": "Long",
      "entry": 16.1593,
      "exit": 16.147,
      "size": 184.0,
      "pnl": -2.26,
      "commission": 0.55,
      "net": -3.66,
      "account": "ZIMDASE9C64",
      "side": "BUY",
      "quantity": 184.0,
      "price": 16.1593
    },
    {
      "date": "2026-02-12",
      "opened": "02/12/26 16:10:02",
      "closed": "16:14:12",
      "held": "00:04:10",
      "symbol": "MGRT",
      "type": "Short",
      "entry": 11.8475,
      "exit": 11.4338,
      "size": 40.0,
      "pnl": 16.55,
      "commission": 0.12,
      "net": 16.55,
      "account": "ZIMDASE9C64",
      "side": "SELL",
      "quantity": 40.0,
      "price": 11.8475
    },
    {
      "date": "2026-02-12",
      "opened": "02/12/26 16:39:27",
      "closed": "16:56:58",
      "held": "00:17:31",
      "symbol": "PINS",
      "type": "Short",
      "entry": 16.25,
      "exit": 15.906,
      "size": 5.0,
      "pnl": 1.72,
      "commission": 0.02,
      "net": 1.71,
      "account": "ZIMDASE9C64",
      "side": "SELL",
      "quantity": 5.0,
      "price": 16.25
    },
    {
      "date": "2026-02-12",
      "opened": "02/12/26 16:45:34",
      "closed": "18:48:28",
      "held": "02:02:54",
      "symbol": "HXHX",
      "type": "Short",
      "entry": 0.7874,
      "exit": 0.7708,
      "size": 130.0,
      "pnl": 2.16,
      "commission": 0.39,
      "net": 1.6,
      "account": "ZIMDASE9C64",
      "side": "SELL",
      "quantity": 130.0,
      "price": 0.7874
    },
    {
      "date": "2026-02-12",
      "opened": "02/12/26 16:52:44",
      "closed": "17:06:05",
      "held": "00:13:21",
      "symbol": "CRSR",
      "type": "Short",
      "entry": 6.0333,
      "exit": 5.9833,
      "size": 30.0,
      "pnl": 1.5,
      "commission": 0.09,
      "net": 1.41,
      "account": "ZIMDASE9C64",
      "side": "SELL",
      "quantity": 30.0,
      "price": 6.0333
    },
    {
      "date": "2026-02-12",
      "opened": "02/12/26 17:28:06",
      "closed": "18:47:45",
      "held": "01:19:39",
      "symbol": "QNCX",
      "type": "Short",
      "entry": 0.2903,
      "exit": 0.2798,
      "size": 100.0,
      "pnl": 1.05,
      "commission": 0.3,
      "net": 0.7,
      "account": "ZIMDASE9C64",
      "side": "SELL",
      "quantity": 100.0,
      "price": 0.2903
    },
    {
      "date": "2026-02-12",
      "opened": "02/12/26 17:48:40",
      "closed": "19:27:10",
      "held": "01:38:30",
      "symbol": "MIMI",
      "type": "Short",
      "entry": 0.5207,
      "exit": 0.5561,
      "size": 210.0,
      "pnl": -7.42,
      "commission": 0.63,
      "net": -8.34,
      "account": "ZIMDASE9C64",
      "side": "SELL",
      "quantity": 210.0,
      "price": 0.5207
    },
    {
      "date": "2026-02-12",
      "opened": "02/12/26 18:32:56",
      "closed": "18:34:28",
      "held": "00:01:32",
      "symbol": "IBIT",
      "type": "Long",
      "entry": 37.613,
      "exit": 37.57,
      "size": 80.0,
      "pnl": -3.44,
      "commission": 0.24,
      "net": -3.94,
      "account": "ZIMDASE9C64",
      "side": "BUY",
      "quantity": 80.0,
      "price": 37.613
    }
  ],
  "summary": {
    "totalTrades": 18,
    "totalPnL": 42.19,
    "totalCommissions": 3.21,
    "netPnL": 37.36,
    "winningTrades": 11,
    "losingTrades": 7,
    "symbols": [
      "GNLN",
      "MGRT",
      "JDZG",
      "QNCX",
      "PMI",
      "CRSR",
      "JZXN",
      "HXHX",
      "MIMI",
      "IBIT",
      "PINS",
      "TSLA",
      "VRME",
      "FSLY",
      "SMU"
    ]
  },
  "metadata": {
    "reprocessed": true,
    "processedAt": "2026-02-15 15:07:44"
  }
}